[
    {
        "title": "Annies Books",
        "subtitle": "Web presence and location directory for Annies Book Stop group for new and used books",
        "link": "http://anniesbooks.com"
    },
    {
        "title": "RNE Furniture",
        "subtitle": "Website for the Rustic New England Furniture Company featuring the work of Derek Skapars",
        "link": "http://rnefurniture.com"
    },
    {
        "title": "Midnight Riders",
        "subtitle": "Custom Wordpress theme",
        "link": "http://midnightriders.com/"
    }
]